odoo/addons/partner_brand/README.rst
odoo/addons/partner_brand/__init__.py
odoo/addons/partner_brand/__manifest__.py
odoo/addons/partner_brand/i18n/hr.po
odoo/addons/partner_brand/i18n/partner_brand.pot
odoo/addons/partner_brand/i18n/zh_CN.po
odoo/addons/partner_brand/migrations/12.0.2.0.0/post-migration.py
odoo/addons/partner_brand/readme/CONTRIBUTORS.rst
odoo/addons/partner_brand/readme/CREDITS.rst
odoo/addons/partner_brand/readme/DESCRIPTION.rst
odoo/addons/partner_brand/static/description/icon.png
odoo/addons/partner_brand/static/description/index.html
odoo/addons/partner_brand/views/report_template.xml
odoo12_addon_partner_brand-12.0.2.1.0.dist-info/METADATA
odoo12_addon_partner_brand-12.0.2.1.0.dist-info/WHEEL
odoo12_addon_partner_brand-12.0.2.1.0.dist-info/top_level.txt
odoo12_addon_partner_brand-12.0.2.1.0.dist-info/RECORD
