Metadata-Version: 2.1
Name: odoo12-addon-partner-brand
Version: 12.0.2.1.0
Summary: Manage your brands and use them on your documents
Home-page: https://github.com/OCA/sale-workflow
Author: Open Source Integrators,Odoo Community Association (OCA)
Author-email: support@odoo-community.org
License: AGPL-3
Platform: UNKNOWN
Classifier: Programming Language :: Python
Classifier: Framework :: Odoo
Classifier: License :: OSI Approved :: GNU Affero General Public License v3
Classifier: Development Status :: 4 - Beta
Requires-Python: >=3.5
Requires-Dist: odoo12-addon-brand
Requires-Dist: odoo (<12.1dev,>=12.0a)
